odoo/addons/stock_picking_batch_extended_account_sale_type/README.rst
odoo/addons/stock_picking_batch_extended_account_sale_type/__init__.py
odoo/addons/stock_picking_batch_extended_account_sale_type/__manifest__.py
odoo/addons/stock_picking_batch_extended_account_sale_type/i18n/es.po
odoo/addons/stock_picking_batch_extended_account_sale_type/i18n/it.po
odoo/addons/stock_picking_batch_extended_account_sale_type/i18n/stock_picking_batch_extended_account_sale_type.pot
odoo/addons/stock_picking_batch_extended_account_sale_type/models/__init__.py
odoo/addons/stock_picking_batch_extended_account_sale_type/models/res_partner.py
odoo/addons/stock_picking_batch_extended_account_sale_type/models/sale_order_type.py
odoo/addons/stock_picking_batch_extended_account_sale_type/models/stock_batch_picking.py
odoo/addons/stock_picking_batch_extended_account_sale_type/readme/CONTRIBUTORS.rst
odoo/addons/stock_picking_batch_extended_account_sale_type/readme/DESCRIPTION.rst
odoo/addons/stock_picking_batch_extended_account_sale_type/static/description/icon.png
odoo/addons/stock_picking_batch_extended_account_sale_type/static/description/index.html
odoo/addons/stock_picking_batch_extended_account_sale_type/tests/__init__.py
odoo/addons/stock_picking_batch_extended_account_sale_type/tests/test_stock_picking_batch_extended_account_sale_type.py
odoo/addons/stock_picking_batch_extended_account_sale_type/views/sale_order_type_views.xml
odoo_addon_stock_picking_batch_extended_account_sale_type-16.0.1.0.3.dist-info/METADATA
odoo_addon_stock_picking_batch_extended_account_sale_type-16.0.1.0.3.dist-info/WHEEL
odoo_addon_stock_picking_batch_extended_account_sale_type-16.0.1.0.3.dist-info/top_level.txt
odoo_addon_stock_picking_batch_extended_account_sale_type-16.0.1.0.3.dist-info/RECORD
